tesla_wall_connector/__init__.py
tesla_wall_connector/api.py
tesla_wall_connector/exceptions.py
tesla_wall_connector/lifetime.py
tesla_wall_connector/version.py
tesla_wall_connector/vitals.py
tesla_wall_connector/wall_connector.py
tesla_wall_connector-1.1.0.dist-info/LICENSE.md
tesla_wall_connector-1.1.0.dist-info/METADATA
tesla_wall_connector-1.1.0.dist-info/WHEEL
tesla_wall_connector-1.1.0.dist-info/RECORD
