Metadata-Version: 2.1
Name: tesla-wall-connector
Version: 1.1.0
Summary: API Library for communicating with a Tesla Wall Connector
Home-page: https://github.com/einarhauks/tesla-wall-connector
License: MIT
Keywords: tesla,wall connector
Author: Einar Bragi Hauksson
Author-email: einar.hauksson@gmail.com
Requires-Python: >=3.8,<4.0
Classifier: License :: OSI Approved :: MIT License
Classifier: Programming Language :: Python :: 3
Classifier: Programming Language :: Python :: 3.8
Classifier: Programming Language :: Python :: 3.9
Classifier: Programming Language :: Python :: 3.10
Classifier: Programming Language :: Python :: 3.11
Classifier: Programming Language :: Python :: 3.12
Requires-Dist: aiohttp (>=3.7.4,<4.0.0)
Requires-Dist: backoff (>=1.11.1)
Project-URL: Repository, https://github.com/einarhauks/tesla-wall-connector
